openscad_runner/__init__.py
openscad_runner-1.2.2.dist-info/licenses/LICENSE
openscad_runner-1.2.2.dist-info/METADATA
openscad_runner-1.2.2.dist-info/WHEEL
openscad_runner-1.2.2.dist-info/top_level.txt
openscad_runner-1.2.2.dist-info/RECORD
