Metadata-Version: 2.4
Name: openscad_runner
Version: 1.2.2
Summary: A Python library to interface with the OpenSCAD app.
Author-email: Revar Desmera <revarbat@gmail.com>
Maintainer-email: Revar Desmera <revarbat@gmail.com>
License-Expression: MIT
Project-URL: Homepage, https://github.com/belfryscad/openscad_runner
Project-URL: Repository, https://github.com/belfryscad/openscad_runner
Project-URL: Bug Tracker, https://github.com/belfryscad/openscad_runner/issues
Project-URL: Releases, https://github.com/belfryscad/openscad_runner/releases
Project-URL: Usage, https://github.com/belfryscad/openscad_runner/README.rst
Project-URL: Documentation, https://github.com/belfryscad/openscad_runner/README.rst
Keywords: openscad,interface
Classifier: Development Status :: 5 - Production/Stable
Classifier: Environment :: Console
Classifier: Intended Audience :: Developers
Classifier: Intended Audience :: Manufacturing
Classifier: Operating System :: MacOS :: MacOS X
Classifier: Operating System :: Microsoft :: Windows
Classifier: Operating System :: POSIX
Classifier: Programming Language :: Python :: 3
Classifier: Topic :: Artistic Software
Classifier: Topic :: Multimedia :: Graphics :: 3D Modeling
Classifier: Topic :: Multimedia :: Graphics :: 3D Rendering
Classifier: Topic :: Software Development :: Libraries
Classifier: Topic :: Software Development :: Libraries :: Python Modules
Requires-Python: >=3.7
License-File: LICENSE
Requires-Dist: Pillow>=7.2.0
Requires-Dist: pygifsicle>=1.0.2
Requires-Dist: apng>=0.3.4
Dynamic: license-file
